{
  "V": {
    "tagline": "胜利是唯一终点",
    "description": "你把棋局当竞技场，无论比分如何，心里那根「赢」的弦从未松懈。落后时你是最危险的对手——因为你不会放弃，只会寻找翻盘的时机。这种对胜利的专注让你在紧张对局中展现出冷静与韧性。",
    "strengths": [
      "落后局面仍保持强烈竞争意志",
      "能清晰识别并执行致胜路径",
      "高度目标导向，不容易分心放弃"
    ],
    "blind_spots": [
      "在意结果多于过程，有时会错过游戏本身的趣味",
      "与同乐型玩家对局时，竞争强度可能引发氛围摩擦"
    ]
  },
  "J": {
    "tagline": "笑声比积分更重要",
    "description": "你打桌游的核心是连结——笑声、话题和共同记忆，是你最在意的「得分」。赢固然开心，但一场让大家情绪高涨的游戏更能让你满足。无论输赢，你都是桌游局里氛围的守护者。",
    "strengths": [
      "天然调节游戏局的整体气氛",
      "细心照顾到桌上每位玩家的体验",
      "让新手在游戏中感到自在和包容"
    ],
    "blind_spots": [
      "在强竞争格局中可能缺乏足够的争胜动力",
      "有时为顾全大局而压抑自己的表现"
    ]
  },
  "I": {
    "tagline": "感觉对了就出手",
    "description": "你信任自己积累出来的盘感，决策快、行动果断，不让自己陷入分析瘫痪。直觉在你手里不是赌博——它是多局对弈沉淀的隐性经验，让你在局面瞬变时能即时应对。",
    "strengths": [
      "行动迅速，不拖累游戏节奏",
      "高压时刻反而更容易激发出色表现",
      "擅长感知整体局势而不拘泥于局部细节"
    ],
    "blind_spots": [
      "有时会漏算关键变量或对手的隐藏意图",
      "在多步骤复杂推演的对局中可能处于结构性劣势"
    ]
  },
  "C": {
    "tagline": "最优解只有一个，我来找它",
    "description": "你喜欢在落子之前把每一个有意义的可能性都在脑海里过一遍。对手的下一步，你已经演练了三遍。这种系统化的思维方式让你在信息充分的局面下表现极其稳定，是桌游局里最可靠的策略担当。",
    "strengths": [
      "决策质量高，极少犯低级失误",
      "擅长识别并预判对手的行为模式",
      "在信息充分的博弈场合具有天然优势"
    ],
    "blind_spots": [
      "决策速度较慢，有时导致游戏节奏拖沓",
      "面对高随机性局面时，推演框架可能完全失效"
    ]
  },
  "R": {
    "tagline": "险棋，才是好棋",
    "description": "你对不确定性有天然的兴奋感，落后时你的眼睛反而更亮——那正是走险棋的最佳时机。「要么赢得漂亮，要么输得爽快」是你的游戏哲学，你给每一场对局带来最多的戏剧性。",
    "strengths": [
      "落后场面常能凭险棋完成意外翻盘",
      "对高风险高回报的机会有敏锐的嗅觉",
      "让整个游戏桌的紧张感和观赏性大幅提升"
    ],
    "blind_spots": [
      "优势明显时仍可能冒不必要的险，白白浪费先机",
      "低风险稳定策略类游戏的快感对你而言往往不足"
    ]
  },
  "S": {
    "tagline": "守住场面，胜利自来",
    "description": "你更信任稳扎稳打的力量。一旦建立了优势，你会选择锁定而不是继续冒险。你深知桌游里最常输掉的不是战略失误，而是那多走的一步险棋——而你从不犯这个错。",
    "strengths": [
      "不会因冲动而浪费已建立的优势",
      "在持久战中优势积累稳定且可预期",
      "擅长把有利局面平稳转化为最终胜利"
    ],
    "blind_spots": [
      "落后场面时翻盘意愿和手段相对有限",
      "在随机翻盘机制较强的游戏里体验可能欠佳"
    ]
  },
  "T": {
    "tagline": "坐进去，把自己变成游戏的一部分",
    "description": "你不只是在玩游戏，你是在进入一个世界——它的美术、叙事、随机戏剧性共同构成了你最享受的体验。骰子的翻转、意外的卡牌、命运的逆转对你来说不是干扰，是剧情高潮。你选游戏，首先看的是它有没有那股把你「吸进去」的气质。",
    "strengths": [
      "对叙事体验和视觉美感有极强的感知与共鸣能力",
      "在充满随机戏剧性的游戏中始终保持高昂投入",
      "向朋友推荐游戏时擅长以感性描述打动人心"
    ],
    "blind_spots": [
      "可能受主题滤镜影响，购入后发现体验不符预期",
      "在纯推演低随机的策略游戏中代入感相对有限"
    ]
  },
  "M": {
    "tagline": "规则越精密，游戏越好玩",
    "description": "你的大脑天然把游戏抽象成一套可以优化的系统。间接竞争、资源效率、机制互动——你在「骰子管不了我」的掌控感中找到最大乐趣。一个优雅的规则设计给你带来的满足感，和别人看到精彩叙事时一样强烈，只是来源不同。",
    "strengths": [
      "能快速理解并分析游戏的底层设计逻辑",
      "在信息充分、策略深度高的博弈中具有天然优势",
      "擅长多步骤规划，不依赖随机事件建立优势"
    ],
    "blind_spots": [
      "随机事件频繁的游戏会打乱你的规划节奏",
      "对叙事驱动和美术导向的游戏吸引力感知较弱"
    ]
  },
  "E": {
    "tagline": "世界那么大，每局都是新发现",
    "description": "你最享受的是那种「第一局」的感觉——全新的规则、未知的策略空间、一切都在摸索中。规则轻巧能开打是加分项，游戏清单永远有新名字才是常态。你是圈子里的风向标，总是第一批尝试新游戏并把朋友拉进来的人。",
    "strengths": [
      "桌游涉猎广泛，能向不同口味的玩家精准推荐",
      "对新机制和新系统保持高度开放的好奇心",
      "能把零碎的空余时间转化为高质量的游戏体验"
    ],
    "blind_spots": [
      "可能购入大量游戏却难以深度钻研任何一款",
      "对已熟悉游戏的重复性可能逐渐失去耐心"
    ]
  },
  "X": {
    "tagline": "把一款游戏玩到没有人能比你更深入",
    "description": "你的游戏柜可能不算大，但每一款你都玩得比任何人都透彻。一两个小时的规则教学不是门槛，是仪式感的开始。反复推演、发现新的策略层次、与旗鼓相当的对手切磋高手对局——这才是你最享受桌游的方式。深度是你衡量一款游戏价值的核心标准。",
    "strengths": [
      "在熟悉游戏中展现出卓越的策略深度与执行精准度",
      "愿意并擅长投入时间学习和驾驭复杂规则系统",
      "是高手对局中最受欢迎且最可靠的游戏伙伴"
    ],
    "blind_spots": [
      "游戏涉猎相对集中，面对陌生游戏初期可能有适应代价",
      "游戏伙伴的耐心和规则理解门槛有时成为体验瓶颈"
    ]
  },
  "F": {
    "tagline": "上桌就是为了大家一起嗨",
    "description": "对你而言桌游是社交的最佳载体——游戏只是创造笑声和话题的工具。游戏途中跑题聊起生活、哄堂大笑、争论规则，都是体验的一部分。你打出的不是棋子，而是人与人之间的连结。",
    "strengths": [
      "天然活跃和提升桌游局的整体气氛",
      "是将桌游新人轻松引入圈子的最好伙伴",
      "对不同游戏口味的玩家都有极强的社交兼容性"
    ],
    "blind_spots": [
      "在需要高度专注的重策略游戏中表现可能受制约",
      "与高沉浸型玩家对局时，游戏体验预期差距较大"
    ]
  },
  "D": {
    "tagline": "上桌，进入状态，全情投入",
    "description": "你对待每一步落子都充满认真，游戏桌对你是一个需要完全专注的竞技场。局面陷入深思时，你是最享受其中的那个人。桌游是你用来磨练判断力、体验纯粹计算乐趣的专属空间。",
    "strengths": [
      "对决策的深度和精准有极高的追求和执行力",
      "在安静专注的游戏环境中往往发挥最佳",
      "是「认真局」里大家最欢迎的游戏伙伴"
    ],
    "blind_spots": [
      "嘈杂或随意的游戏环境会显著降低体验满意度",
      "对以社交互动为核心的游戏可能热情相对较低"
    ]
  }
}